repe/__init__.py
repe/pipelines.py
repe/rep_control_contrast_vec.py
repe/rep_control_pipeline.py
repe/rep_control_reading_vec.py
repe/rep_readers.py
repe/rep_reading_pipeline.py
repe-0.1.3.dist-info/LICENSE
repe-0.1.3.dist-info/METADATA
repe-0.1.3.dist-info/WHEEL
repe-0.1.3.dist-info/top_level.txt
repe-0.1.3.dist-info/RECORD
