Metadata-Version: 2.1
Name: repe
Version: 0.1.3
Summary: Representation Engineering
Project-URL: Homepage, https://github.com/andyzoujm/representation-engineering
Project-URL: Issues, https://github.com/andyzoujm/representation-engineering/issues
Classifier: Programming Language :: Python :: 3
Classifier: License :: OSI Approved :: MIT License
Classifier: Operating System :: OS Independent
Requires-Python: >=3.9
License-File: LICENSE
Requires-Dist: accelerate
Requires-Dist: scikit-learn
Requires-Dist: transformers
